grast/__init__.py
grast/cfg.py
grast/delta/__init__.py
grast/delta/algebra.py
grast/delta/delta.py
grast/dual.py
grast/forward.py
grast/grad.py
grast/py.typed
grast/real/__init__.py
grast/real/algebra.py
grast/real/binary.py
grast/real/real.py
grast/real/unary.py
grast/utils/__init__.py
grast/utils/to_string/__init__.py
grast/utils/to_string/delta_str.py
grast/utils/to_string/real_str.py
grast/utils/to_string/utils.py
grast-0.1.2.dist-info/LICENSE
grast-0.1.2.dist-info/METADATA
grast-0.1.2.dist-info/WHEEL
grast-0.1.2.dist-info/RECORD
