Metadata-Version: 2.1
Name: grast
Version: 0.1.2
Summary: Lazy automatic differentiation for Python
Author: cospectrum
Author-email: severinalexeyv@gmail.com
Requires-Python: >=3.10,<4.0
Classifier: Programming Language :: Python :: 3
Classifier: Programming Language :: Python :: 3.10
Classifier: Programming Language :: Python :: 3.11
